{"name":"发布","slug":"发布","count":1,"postlist":[{"title":"前端-发布一个npm组件","uid":"952c9825449951f4be9b496ff7057cc8","slug":"前端-发布一个npm组件","date":"2023-02-20T16:02:37.000Z","updated":"2023-02-20T18:09:11.003Z","comments":true,"path":"api/articles/前端-发布一个npm组件.json","keywords":null,"cover":"https://api.r10086.com:8443/%E5%9B%BE%E5%8C%85/%E9%A3%8E%E6%99%AF%E7%B3%BB%E5%88%971/107299.jpg","text":"发布一个npm组件 最近整了一个css的展开收起，想着发布一个npm组件，就顺手记录一下 一、准备一个项目 有一个现成的仓库，那就用这个改吧 link: https://github.com/yyyz1011/leaf_collapse_component 二、组件修改 新增pa...","link":"","photos":[],"count_time":{"symbolsCount":"3.5k","symbolsTime":"3 mins."},"categories":[{"name":"前端","slug":"前端","count":6,"path":"api/categories/前端.json"}],"tags":[{"name":"发布","slug":"发布","count":1,"path":"api/tags/发布.json"}],"author":{"name":"YeZhou","slug":"blog-author","avatar":"https://avatars.githubusercontent.com/u/65165470?v=4","link":"/","description":"心在路上 路在心里","socials":{"github":"","twitter":"","stackoverflow":"","wechat":"","qq":"","weibo":"","zhihu":"","csdn":"","juejin":"","customs":{"github":{"icon":"/svg/github.svg","link":"https://github.com/yyyz1011"},"douyin":{"icon":"/svg/douyin.svg","link":"https://www.douyin.com/user/MS4wLjABAAAA6ifrwjSFlBcGKpQG3djw2qcrqpJ1eWsosnhMLlsJiJc"},"tuchong":{"icon":"/svg/tuchong.svg","link":"https://tuchong.com/27088635/?utm_source=weixin&utm_medium=android_share"},"bilibili":{"icon":"/svg/bilibili.svg","link":"https://space.bilibili.com/393187584?spm_id_from=333.1007.0.0"}}}},"feature":true}]}